README.md
setup.py
dw8000_wav2syx/__init__.py
dw8000_wav2syx/__main__.py
dw8000_wav2syx/dw8000_bin2syx.py
dw8000_wav2syx/dw8000_reverse_engineer.py
dw8000_wav2syx/dw8000_wav2bin.py
dw8000_wav2syx_christofmuc.egg-info/PKG-INFO
dw8000_wav2syx_christofmuc.egg-info/SOURCES.txt
dw8000_wav2syx_christofmuc.egg-info/dependency_links.txt
dw8000_wav2syx_christofmuc.egg-info/entry_points.txt
dw8000_wav2syx_christofmuc.egg-info/requires.txt
dw8000_wav2syx_christofmuc.egg-info/top_level.txt