Metadata-Version: 2.1
Name: dw8000-wav2syx-christofmuc
Version: 1.0.7
Summary: Convert data for the Korg DW8000 stored as tape wav files into MIDI sysex format.
Home-page: https://github.com/christofmuc/dw8000_wav2syx
Author: Christof
Author-email: christof.ruch@gmail.com
License: UNKNOWN
Platform: UNKNOWN
Classifier: Programming Language :: Python :: 3
Classifier: Operating System :: OS Independent
Requires-Python: >=3.6
